rabbitmq_async_client/__init__.py
rabbitmq_async_client/config_logs.py
rabbitmq_async_client/rabbitmq_client.py
tests/__init__.py
tests/conf_rabbit.py
tests/cosumer.py
tests/init_queues.py
tests/publisher.py
tests/pull.py
tests/push.py
rabbitmq_async_client-0.1.1.dist-info/LICENSE
rabbitmq_async_client-0.1.1.dist-info/METADATA
rabbitmq_async_client-0.1.1.dist-info/WHEEL
rabbitmq_async_client-0.1.1.dist-info/top_level.txt
rabbitmq_async_client-0.1.1.dist-info/RECORD
